norepeat/__init__.py
norepeat/__main__.py
norepeat/count_code_nums.py
norepeat/diff_file.py
norepeat/download_img.py
norepeat/gen_markdown_menu.py
norepeat/merge_dir.py
norepeat/rename_file.py
norepeat/spell_check.py
norepeat/split_dir.py
norepeat-1.1.0.dist-info/LICENSE
norepeat-1.1.0.dist-info/METADATA
norepeat-1.1.0.dist-info/WHEEL
norepeat-1.1.0.dist-info/entry_points.txt
norepeat-1.1.0.dist-info/top_level.txt
norepeat-1.1.0.dist-info/RECORD
