Metadata-Version: 2.1
Name: norepeat
Version: 1.1.0
Summary: Less codes make more tools
Home-page: https://github.com/DasyDong/python-norepeat
Author: Dasy Dong
Author-email: dasydong@gmail.com
License: MIT
Platform: UNKNOWN
Classifier: License :: OSI Approved :: MIT License
Classifier: Programming Language :: Python :: 3
Requires-Dist: pyenchant
